{
  "titluText": "Contact",
  "imagePath": "asset/image/tandemuloncescu.jpg",
  "buttonsList": [
    {
      "icon": "facebook",
      "header": "Facebook",
      "buttonContent": "blabla bla aici puteti vedea pagina noastra de fb",
      "label": "facebook.com",
      "link": "https://www.facebook.com/laurentiu.oncescu"
    },
    {
      "icon": "instagram",
      "header": "Facebook",
      "buttonContent": "blabla bla aici puteti vedea pagina noastra de fb",
      "label": "facebook.com",
      "link": "https://www.facebook.com/laurentiu.oncescu"
    },
    {
      "icon": "earth",
      "header": "Facebook",
      "buttonContent": "blabla bla aici puteti vedea pagina noastra de fb",
      "label": "facebook.com",
      "link": "https://www.facebook.com/laurentiu.oncescu"
    },
    {
      "icon": "info",
      "header": "Facebook",
      "buttonContent": "blabla bla aici puteti vedea pagina noastra de fb",
      "label": "facebook.com",
      "link": "https://www.facebook.com/laurentiu.oncescu"
    }
  ]
}